jason2024_bmi/bmi_calculator.py
jason2024_bmi/bmi_test2.py
jason2024_bmi-0.0.0.3.dist-info/METADATA
jason2024_bmi-0.0.0.3.dist-info/WHEEL
jason2024_bmi-0.0.0.3.dist-info/top_level.txt
jason2024_bmi-0.0.0.3.dist-info/RECORD
