Metadata-Version: 2.1
Name: jason2024-bmi
Version: 0.0.0.3
Summary: My Second Test
Home-page: https://www.naver.com
Author: Ju Dang
Author-email: david766589@gmail.com
License: MIT
Requires-Python: >=3.6
